yapg/__init__.py
yapg/__main__.py
yapg/dictionary.txt
yapg-0.0.9.dist-info/LICENSE
yapg-0.0.9.dist-info/METADATA
yapg-0.0.9.dist-info/WHEEL
yapg-0.0.9.dist-info/top_level.txt
yapg-0.0.9.dist-info/RECORD
