Metadata-Version: 2.1
Name: yapg
Version: 0.0.9
Summary: Yet Another Password Generator - A simple password generator checking password complexity with zxcvbn
Home-page: https://pypi.org/project/yapg/
Author: Alexandre Janvrin
Author-email: alexandre.janvrin@reseau.eseo.fr
License: UNKNOWN
Platform: UNKNOWN
Classifier: Programming Language :: Python :: 3
Classifier: License :: OSI Approved :: GNU Affero General Public License v3
Classifier: Operating System :: POSIX :: Linux
Requires-Python: >=3.6
Requires-Dist: zxcvbn
